app/__init__.py
app/helper.py
app/useful_app.py
cli_jam-0.1.2.dist-info/entry_points.txt
cli_jam-0.1.2.dist-info/WHEEL
cli_jam-0.1.2.dist-info/METADATA
cli_jam-0.1.2.dist-info/RECORD
