Metadata-Version: 2.1
Name: cli-jam
Version: 0.1.2
Summary: A very useful app.
Author: Chris Webster
Author-email: chris@dataq.co.za
Requires-Python: >=3.8,<4.0
Classifier: Programming Language :: Python :: 3
Classifier: Programming Language :: Python :: 3.8
Classifier: Programming Language :: Python :: 3.9
Requires-Dist: typer (>=0.4.1,<0.5.0)
